taiga_client/__init__.py
taiga_client/taiga_client.py
taiga_client-1.1.1.dist-info/LICENSE
taiga_client-1.1.1.dist-info/METADATA
taiga_client-1.1.1.dist-info/WHEEL
taiga_client-1.1.1.dist-info/top_level.txt
taiga_client-1.1.1.dist-info/RECORD
