Metadata-Version: 2.1
Name: taiga-client
Version: 1.1.1
Summary: A Python client for Taiga Rest API
Home-page: https://github.com/Alextanker/taiga-client
Author: Alextanker
Author-email: alextanker@kionclient.pro
Classifier: Programming Language :: Python :: 3
Classifier: License :: OSI Approved :: MIT License
Classifier: Operating System :: OS Independent
Requires-Python: >=3.6
License-File: LICENSE
Requires-Dist: requests
